CHANGELOG.md
LICENSE
MANIFEST.in
Makefile
README.md
customqueries.json
pyproject.toml
doc/bloodhound_clusters.png
hashcathelper/__init__.py
hashcathelper/__main__.py
hashcathelper/_meta.py
hashcathelper/analytics.py
hashcathelper/args.py
hashcathelper/bloodhound.py
hashcathelper/bloodhound.py.orig
hashcathelper/consts.py
hashcathelper/hashcat.py
hashcathelper/log.py
hashcathelper/md4.py
hashcathelper/reporting.py
hashcathelper/sql.py
hashcathelper/toggles-lm-ntlm.rule
hashcathelper/utils.py
hashcathelper.egg-info/PKG-INFO
hashcathelper.egg-info/SOURCES.txt
hashcathelper.egg-info/dependency_links.txt
hashcathelper.egg-info/entry_points.txt
hashcathelper.egg-info/requires.txt
hashcathelper.egg-info/top_level.txt
hashcathelper/__pycache__/__init__.cpython-310.pyc
hashcathelper/__pycache__/__init__.cpython-311.pyc
hashcathelper/__pycache__/__main__.cpython-310.pyc
hashcathelper/__pycache__/__main__.cpython-311.pyc
hashcathelper/__pycache__/_meta.cpython-310.pyc
hashcathelper/__pycache__/_meta.cpython-311.pyc
hashcathelper/__pycache__/analytics.cpython-310.pyc
hashcathelper/__pycache__/analytics.cpython-311.pyc
hashcathelper/__pycache__/args.cpython-310.pyc
hashcathelper/__pycache__/args.cpython-311.pyc
hashcathelper/__pycache__/bloodhound.cpython-310.pyc
hashcathelper/__pycache__/bloodhound.cpython-311.pyc
hashcathelper/__pycache__/consts.cpython-310.pyc
hashcathelper/__pycache__/consts.cpython-311.pyc
hashcathelper/__pycache__/hashcat.cpython-310.pyc
hashcathelper/__pycache__/log.cpython-310.pyc
hashcathelper/__pycache__/log.cpython-311.pyc
hashcathelper/__pycache__/md4.cpython-310.pyc
hashcathelper/__pycache__/md4.cpython-311.pyc
hashcathelper/__pycache__/reporting.cpython-310.pyc
hashcathelper/__pycache__/reporting.cpython-311.pyc
hashcathelper/__pycache__/sql.cpython-310.pyc
hashcathelper/__pycache__/sql.cpython-311.pyc
hashcathelper/__pycache__/utils.cpython-310.pyc
hashcathelper/__pycache__/utils.cpython-311.pyc
hashcathelper/subcommands/__init__.py
hashcathelper/subcommands/analytics.py
hashcathelper/subcommands/bloodhound.py
hashcathelper/subcommands/db.py
hashcathelper/subcommands/ntlm.py
hashcathelper/subcommands/__pycache__/__init__.cpython-310.pyc
