Metadata-Version: 2.1
Name: hashcathelper
Version: 1.0.0
Summary: Convenience tool for hashcat
Author-email: Adrian Vollmer <adrian.vollmer@syss.de>
License: MIT License
Project-URL: Homepage, https://github.com/SySS-Research/hashcathelper
Project-URL: Bug Tracker, https://github.com/SySS-Research/hashcathelper/issues
Keywords: hashcat,passwords,cracking,bloodhound,analytics,pentest
Classifier: License :: OSI Approved :: MIT License
Classifier: Programming Language :: Python
Classifier: Programming Language :: Python :: 3
Requires-Python: >=3.7
License-File: LICENSE
Requires-Dist: pyxdg
Requires-Dist: sqlalchemy
Requires-Dist: tabulate
Requires-Dist: openpyxl
Requires-Dist: neo4j>=4.2
Requires-Dist: importlib-metadata
Requires-Dist: tqdm
Provides-Extra: postgres
Requires-Dist: psycopg2; extra == "postgres"
Provides-Extra: tests
Requires-Dist: pytest; extra == "tests"
Requires-Dist: flake8; extra == "tests"
Requires-Dist: beautifulsoup4; extra == "tests"
Requires-Dist: lxml; extra == "tests"
Provides-Extra: dev
Requires-Dist: tox; extra == "dev"
Requires-Dist: build; extra == "dev"
